bookkeywords/__init__.py
bookkeywords/bookwords.py
bookkeywords-2.1.0.dist-info/METADATA
bookkeywords-2.1.0.dist-info/WHEEL
bookkeywords-2.1.0.dist-info/top_level.txt
bookkeywords-2.1.0.dist-info/RECORD
